nlplite/__init__.py
nlplite/automaton.py
nlplite/cli.py
nlplite/extractor.py
nlplite/negation.py
nlplite/py.typed
nlplite/utils.py
nlplite-0.2.0.dist-info/licenses/LICENSE
nlplite-0.2.0.dist-info/METADATA
nlplite-0.2.0.dist-info/WHEEL
nlplite-0.2.0.dist-info/entry_points.txt
nlplite-0.2.0.dist-info/top_level.txt
nlplite-0.2.0.dist-info/RECORD
