Metadata-Version: 2.4
Name: nlplite
Version: 0.2.0
Summary: Fast lightweight NLP library for concept and segment extraction with negation/uncertainty detection.
Author-email: Vidul Panickan <apvidul@gmail.com>
License: MIT
Requires-Python: >=3.8
License-File: LICENSE
Requires-Dist: pyahocorasick
Dynamic: license-file
